{
    "events": [
        {
            "id": 1,
            "year": "2021",
            "location": "الجامعة الامريكية",
            "date": "24 Jun 2020",
            "title": "كيف تاتى بالوان متناسقة لتصميمك",
            "cover": "event3.jpg",
            "description": "كل ما تحتاج اليه هو وسيلة تمكنك من التعلم بمفردك و فى البيت بابسط الطرق و فى مجالات عديدة مجانى و باشتراك مميز مناسب للجميع",
            "speakers": [
                {
                    "name": "محمد على",
                    "cover": "mohamed.jpg",
                    "bio": "مدرب معتمد من شركة ادوبى و مصمم جرافيك وMotion Artist خبرة 10 سنين فى مجال الجرافيك والموشن جرافيك"
                },
                {
                    "name": "كريم على",
                    "cover": "karim.jpg",
                    "bio": "مدرب معتمد من شركة ادوبى و مصمم جرافيك وMotion Artist خبرة 10 سنين فى مجال الجرافيك والموشن جرافيك"
                }
            ]
        },
        {
            "id": 2,
            "year": "2021",
            "location": "الجامعة الامريكية",
            "date": "24 Jun 2020",
            "title": "معانى الالوان و توظيفها فى التصميم",
            "cover": "event1.jpg",
            "description": "كل ما تحتاج اليه هو وسيلة تمكنك من التعلم بمفردك و فى البيت بابسط الطرق و فى مجالات عديدة مجانى و باشتراك مميز مناسب للجميع",
            "speakers": [
                {
                    "name": "محمد على",
                    "cover": "mohamed.jpg",
                    "bio": "مدرب معتمد من شركة ادوبى و مصمم جرافيك وMotion Artist خبرة 10 سنين فى مجال الجرافيك والموشن جرافيك"
                },
                {
                    "name": "كريم على",
                    "cover": "karim.jpg",
                    "bio": "مدرب معتمد من شركة ادوبى و مصمم جرافيك وMotion Artist خبرة 10 سنين فى مجال الجرافيك والموشن جرافيك"
                }
            ]
        },
        {
            "id": 3,
            "year": "2021",
            "location": "الجامعة الامريكية",
            "date": "24 Jun 2020",
            "title": "كيفية العمل على برنامج الفوتوشوب",
            "cover": "events7.png",
            "description": "كل ما تحتاج اليه هو وسيلة تمكنك من التعلم بمفردك و فى البيت بابسط الطرق و فى مجالات عديدة مجانى و باشتراك مميز مناسب للجميع",
            "speakers": [
                {
                    "name": "محمد على",
                    "cover": "mohamed.jpg",
                    "bio": "مدرب معتمد من شركة ادوبى و مصمم جرافيك وMotion Artist خبرة 10 سنين فى مجال الجرافيك والموشن جرافيك"
                },
                {
                    "name": "كريم على",
                    "cover": "karim.jpg",
                    "bio": "مدرب معتمد من شركة ادوبى و مصمم جرافيك وMotion Artist خبرة 10 سنين فى مجال الجرافيك والموشن جرافيك"
                }
            ]
        },
        {
            "id": 4,
            "year": "2021",
            "location": "الجامعة الامريكية",
            "date": "24 Jun 2020",
            "title": "كيف تاتى بالوان متناسقة لتصميمك",
            "cover": "events8.png",
            "description": "كل ما تحتاج اليه هو وسيلة تمكنك من التعلم بمفردك و فى البيت بابسط الطرق و فى مجالات عديدة مجانى و باشتراك مميز مناسب للجميع",
            "speakers": [
                {
                    "name": "محمد على",
                    "cover": "mohamed.jpg",
                    "bio": "مدرب معتمد من شركة ادوبى و مصمم جرافيك وMotion Artist خبرة 10 سنين فى مجال الجرافيك والموشن جرافيك"
                },
                {
                    "name": "كريم على",
                    "cover": "karim.jpg",
                    "bio": "مدرب معتمد من شركة ادوبى و مصمم جرافيك وMotion Artist خبرة 10 سنين فى مجال الجرافيك والموشن جرافيك"
                }
            ]
        },
        {
            "id": 5,
            "year": "2021",
            "location": "الجامعة الامريكية",
            "date": "24 Jun 2020",
            "title": "كيف تاتى بالوان متناسقة لتصميمك",
            "cover": "events5.png",
            "description": "كل ما تحتاج اليه هو وسيلة تمكنك من التعلم بمفردك و فى البيت بابسط الطرق و فى مجالات عديدة مجانى و باشتراك مميز مناسب للجميع",
            "speakers": [
                {
                    "name": "محمد على",
                    "cover": "mohamed.jpg",
                    "bio": "مدرب معتمد من شركة ادوبى و مصمم جرافيك وMotion Artist خبرة 10 سنين فى مجال الجرافيك والموشن جرافيك"
                },
                {
                    "name": "كريم على",
                    "cover": "karim.jpg",
                    "bio": "مدرب معتمد من شركة ادوبى و مصمم جرافيك وMotion Artist خبرة 10 سنين فى مجال الجرافيك والموشن جرافيك"
                }
            ]
        },
        {
            "id": 6,
            "year": "2021",
            "location": "الجامعة الامريكية",
            "date": "24 Jun 2020",
            "title": "كيف تاتى بالوان متناسقة لتصميمك",
            "cover": "events6.png",
            "description": "كل ما تحتاج اليه هو وسيلة تمكنك من التعلم بمفردك و فى البيت بابسط الطرق و فى مجالات عديدة مجانى و باشتراك مميز مناسب للجميع",
            "speakers": [
                {
                    "name": "محمد على",
                    "cover": "mohamed.jpg",
                    "bio": "مدرب معتمد من شركة ادوبى و مصمم جرافيك وMotion Artist خبرة 10 سنين فى مجال الجرافيك والموشن جرافيك"
                },
                {
                    "name": "كريم على",
                    "cover": "karim.jpg",
                    "bio": "مدرب معتمد من شركة ادوبى و مصمم جرافيك وMotion Artist خبرة 10 سنين فى مجال الجرافيك والموشن جرافيك"
                }
            ]
        }
    ]
}